[{"normalizedCode":"IOBADEFF","sourceCount":1,"lastVerified":"2026-05-18T00:00:00Z","confidence":80,"sources":["internal-database"],"conflicts":[],"sourceLog":[],"countryName":"Germany","code":"IOBADEFF","type":"swift","country":"DE","bankName":"Indian Overseas Bank","city":"Frankfurt am Main","isHeadOffice":true},{"normalizedCode":"IOBAUS33","sourceCount":1,"lastVerified":"2026-05-18T00:00:00Z","confidence":80,"sources":["internal-database"],"conflicts":[],"sourceLog":[],"countryName":"United States","code":"IOBAUS33","type":"swift","country":"US","bankName":"Indian Overseas Bank","city":"New York","isHeadOffice":true},{"normalizedCode":"IOBAGB2L","sourceCount":1,"lastVerified":"2026-05-18T00:00:00Z","confidence":80,"sources":["internal-database"],"conflicts":[],"sourceLog":[],"countryName":"United Kingdom","code":"IOBAGB2L","type":"swift","country":"GB","bankName":"Indian Overseas Bank","city":"London","isHeadOffice":true},{"normalizedCode":"IOBAFRPP","sourceCount":1,"lastVerified":"2026-05-18T00:00:00Z","confidence":80,"sources":["internal-database"],"conflicts":[],"sourceLog":[],"countryName":"France","code":"IOBAFRPP","type":"swift","country":"FR","bankName":"Indian Overseas Bank","city":"Paris","isHeadOffice":true},{"normalizedCode":"IOBAJPJT","sourceCount":1,"lastVerified":"2026-05-18T00:00:00Z","confidence":80,"sources":["internal-database"],"conflicts":[],"sourceLog":[],"countryName":"Japan","code":"IOBAJPJT","type":"swift","country":"JP","bankName":"Indian Overseas Bank","city":"Tokyo","isHeadOffice":true},{"normalizedCode":"IOBACNBJ","sourceCount":1,"lastVerified":"2026-05-18T00:00:00Z","confidence":80,"sources":["internal-database"],"conflicts":[],"sourceLog":[],"countryName":"China","code":"IOBACNBJ","type":"swift","country":"CN","bankName":"Indian Overseas Bank","city":"Beijing","isHeadOffice":true},{"normalizedCode":"IOBAHKHH","sourceCount":1,"lastVerified":"2026-05-18T00:00:00Z","confidence":80,"sources":["internal-database"],"conflicts":[],"sourceLog":[],"countryName":"Hong Kong","code":"IOBAHKHH","type":"swift","country":"HK","bankName":"Indian Overseas Bank","city":"Hong Kong","isHeadOffice":true},{"normalizedCode":"IOBASGSG","sourceCount":1,"lastVerified":"2026-05-18T00:00:00Z","confidence":80,"sources":["internal-database"],"conflicts":[],"sourceLog":[],"countryName":"Singapore","code":"IOBASGSG","type":"swift","country":"SG","bankName":"Indian Overseas Bank","city":"Singapore","isHeadOffice":true},{"normalizedCode":"IOBAINBB","sourceCount":1,"lastVerified":"2026-05-18T00:00:00Z","confidence":80,"sources":["internal-database"],"conflicts":[],"sourceLog":[],"countryName":"India","code":"IOBAINBB","type":"swift","country":"IN","bankName":"Indian Overseas Bank","city":"Mumbai","isHeadOffice":true},{"normalizedCode":"IOBAAU33","sourceCount":1,"lastVerified":"2026-05-18T00:00:00Z","confidence":80,"sources":["internal-database"],"conflicts":[],"sourceLog":[],"countryName":"Australia","code":"IOBAAU33","type":"swift","country":"AU","bankName":"Indian Overseas Bank","city":"Melbourne","isHeadOffice":true},{"normalizedCode":"IOBACATT","sourceCount":1,"lastVerified":"2026-05-18T00:00:00Z","confidence":80,"sources":["internal-database"],"conflicts":[],"sourceLog":[],"countryName":"Canada","code":"IOBACATT","type":"swift","country":"CA","bankName":"Indian Overseas Bank","city":"Toronto","isHeadOffice":true},{"normalizedCode":"IOBACHZH","sourceCount":1,"lastVerified":"2026-05-18T00:00:00Z","confidence":80,"sources":["internal-database"],"conflicts":[],"sourceLog":[],"countryName":"Switzerland","code":"IOBACHZH","type":"swift","country":"CH","bankName":"Indian Overseas Bank","city":"Zurich","isHeadOffice":true},{"normalizedCode":"IOBANL2A","sourceCount":1,"lastVerified":"2026-05-18T00:00:00Z","confidence":80,"sources":["internal-database"],"conflicts":[],"sourceLog":[],"countryName":"Netherlands","code":"IOBANL2A","type":"swift","country":"NL","bankName":"Indian Overseas Bank","city":"Amsterdam","isHeadOffice":true},{"normalizedCode":"IOBAITMM","sourceCount":1,"lastVerified":"2026-05-18T00:00:00Z","confidence":80,"sources":["internal-database"],"conflicts":[],"sourceLog":[],"countryName":"Italy","code":"IOBAITMM","type":"swift","country":"IT","bankName":"Indian Overseas Bank","city":"Milan","isHeadOffice":true},{"normalizedCode":"IOBAESMM","sourceCount":1,"lastVerified":"2026-05-18T00:00:00Z","confidence":80,"sources":["internal-database"],"conflicts":[],"sourceLog":[],"countryName":"Spain","code":"IOBAESMM","type":"swift","country":"ES","bankName":"Indian Overseas Bank","city":"Madrid","isHeadOffice":true},{"normalizedCode":"IOBAKRSE","sourceCount":1,"lastVerified":"2026-05-18T00:00:00Z","confidence":80,"sources":["internal-database"],"conflicts":[],"sourceLog":[],"countryName":"South Korea","code":"IOBAKRSE","type":"swift","country":"KR","bankName":"Indian Overseas Bank","city":"Seoul","isHeadOffice":true}]