[{"normalizedCode":"NWBKDEFF","sourceCount":1,"lastVerified":"2026-05-18T00:00:00Z","confidence":80,"sources":["internal-database"],"conflicts":[],"sourceLog":[],"countryName":"Germany","code":"NWBKDEFF","type":"swift","country":"DE","bankName":"NatWest Bank","city":"Frankfurt am Main","isHeadOffice":true},{"normalizedCode":"NWBKUS33","sourceCount":1,"lastVerified":"2026-05-18T00:00:00Z","confidence":80,"sources":["internal-database"],"conflicts":[],"sourceLog":[],"countryName":"United States","code":"NWBKUS33","type":"swift","country":"US","bankName":"NatWest Bank","city":"New York","isHeadOffice":true},{"normalizedCode":"NWBKGB2L","sourceCount":1,"lastVerified":"2026-05-18T00:00:00Z","confidence":80,"sources":["internal-database"],"conflicts":[],"sourceLog":[],"countryName":"United Kingdom","code":"NWBKGB2L","type":"swift","country":"GB","bankName":"NatWest Bank","city":"London","isHeadOffice":true},{"normalizedCode":"NWBKFRPP","sourceCount":1,"lastVerified":"2026-05-18T00:00:00Z","confidence":80,"sources":["internal-database"],"conflicts":[],"sourceLog":[],"countryName":"France","code":"NWBKFRPP","type":"swift","country":"FR","bankName":"NatWest Bank","city":"Paris","isHeadOffice":true},{"normalizedCode":"NWBKJPJT","sourceCount":1,"lastVerified":"2026-05-18T00:00:00Z","confidence":80,"sources":["internal-database"],"conflicts":[],"sourceLog":[],"countryName":"Japan","code":"NWBKJPJT","type":"swift","country":"JP","bankName":"NatWest Bank","city":"Tokyo","isHeadOffice":true},{"normalizedCode":"NWBKCNBJ","sourceCount":1,"lastVerified":"2026-05-18T00:00:00Z","confidence":80,"sources":["internal-database"],"conflicts":[],"sourceLog":[],"countryName":"China","code":"NWBKCNBJ","type":"swift","country":"CN","bankName":"NatWest Bank","city":"Beijing","isHeadOffice":true},{"normalizedCode":"NWBKHKHH","sourceCount":1,"lastVerified":"2026-05-18T00:00:00Z","confidence":80,"sources":["internal-database"],"conflicts":[],"sourceLog":[],"countryName":"Hong Kong","code":"NWBKHKHH","type":"swift","country":"HK","bankName":"NatWest Bank","city":"Hong Kong","isHeadOffice":true},{"normalizedCode":"NWBKSGSG","sourceCount":1,"lastVerified":"2026-05-18T00:00:00Z","confidence":80,"sources":["internal-database"],"conflicts":[],"sourceLog":[],"countryName":"Singapore","code":"NWBKSGSG","type":"swift","country":"SG","bankName":"NatWest Bank","city":"Singapore","isHeadOffice":true},{"normalizedCode":"NWBKINBB","sourceCount":1,"lastVerified":"2026-05-18T00:00:00Z","confidence":80,"sources":["internal-database"],"conflicts":[],"sourceLog":[],"countryName":"India","code":"NWBKINBB","type":"swift","country":"IN","bankName":"NatWest Bank","city":"Mumbai","isHeadOffice":true},{"normalizedCode":"NWBKAU33","sourceCount":1,"lastVerified":"2026-05-18T00:00:00Z","confidence":80,"sources":["internal-database"],"conflicts":[],"sourceLog":[],"countryName":"Australia","code":"NWBKAU33","type":"swift","country":"AU","bankName":"NatWest Bank","city":"Melbourne","isHeadOffice":true},{"normalizedCode":"NWBKCATT","sourceCount":1,"lastVerified":"2026-05-18T00:00:00Z","confidence":80,"sources":["internal-database"],"conflicts":[],"sourceLog":[],"countryName":"Canada","code":"NWBKCATT","type":"swift","country":"CA","bankName":"NatWest Bank","city":"Toronto","isHeadOffice":true},{"normalizedCode":"NWBKCHZH","sourceCount":1,"lastVerified":"2026-05-18T00:00:00Z","confidence":80,"sources":["internal-database"],"conflicts":[],"sourceLog":[],"countryName":"Switzerland","code":"NWBKCHZH","type":"swift","country":"CH","bankName":"NatWest Bank","city":"Zurich","isHeadOffice":true},{"normalizedCode":"NWBKNL2A","sourceCount":1,"lastVerified":"2026-05-18T00:00:00Z","confidence":80,"sources":["internal-database"],"conflicts":[],"sourceLog":[],"countryName":"Netherlands","code":"NWBKNL2A","type":"swift","country":"NL","bankName":"NatWest Bank","city":"Amsterdam","isHeadOffice":true},{"normalizedCode":"NWBKITMM","sourceCount":1,"lastVerified":"2026-05-18T00:00:00Z","confidence":80,"sources":["internal-database"],"conflicts":[],"sourceLog":[],"countryName":"Italy","code":"NWBKITMM","type":"swift","country":"IT","bankName":"NatWest Bank","city":"Milan","isHeadOffice":true},{"normalizedCode":"NWBKESMM","sourceCount":1,"lastVerified":"2026-05-18T00:00:00Z","confidence":80,"sources":["internal-database"],"conflicts":[],"sourceLog":[],"countryName":"Spain","code":"NWBKESMM","type":"swift","country":"ES","bankName":"NatWest Bank","city":"Madrid","isHeadOffice":true},{"normalizedCode":"NWBKKRSE","sourceCount":1,"lastVerified":"2026-05-18T00:00:00Z","confidence":80,"sources":["internal-database"],"conflicts":[],"sourceLog":[],"countryName":"South Korea","code":"NWBKKRSE","type":"swift","country":"KR","bankName":"NatWest Bank","city":"Seoul","isHeadOffice":true}]